{
  "@microsoft/generator-sharepoint": {
    "plusBeta": false,
    "isCreatingSolution": true,
    "nodeVersion": "20.9.0",
    "sdksVersions": {
      "@microsoft/microsoft-graph-client": "3.0.2",
      "@microsoft/teams-js": "2.12.0"
    },
    "version": "1.19.0",
    "libraryName": "test",
    "libraryId": "f00b91b8-4a57-4b32-9bfb-f1e2dc29cd71",
    "environment": "spo",
    "packageManager": "npm",
    "solutionName": "Test",
    "solutionShortDescription": "Test description",
    "skipFeatureDeployment": true,
    "isDomainIsolated": false,
    "componentType": "webpart"
  }
}
